{
    "Ar36": {
        "error": 0.0001718357408946423,
        "error_type": "",
        "fit": "previous",
        "references": [
            {
                "exclude": false,
                "record_id": "ba-01-A-4467"
            }
        ],
        "value": 0.005170957172473316
    },
    "Ar36L2": {
        "error": 0.007585233830312942,
        "error_type": "",
        "fit": "previous",
        "references": [
            {
                "exclude": false,
                "record_id": "ba-01-A-4467"
            }
        ],
        "value": 0.017650719854618496
    },
    "Ar37": {
        "error": 0.006976403227453499,
        "error_type": "",
        "fit": "previous",
        "references": [
            {
                "exclude": false,
                "record_id": "ba-01-A-4467"
            }
        ],
        "value": 0.02577726791959789
    },
    "Ar37L1": {
        "error": 0.021097811429742937,
        "error_type": "",
        "fit": "previous",
        "references": [
            {
                "exclude": false,
                "record_id": "ba-01-A-4467"
            }
        ],
        "value": 0.051132122432454005
    },
    "Ar38": {
        "error": 0.016698579742492566,
        "error_type": "",
        "fit": "previous",
        "references": [
            {
                "exclude": false,
                "record_id": "ba-01-A-4467"
            }
        ],
        "value": 0.04168589409749266
    },
    "Ar38AX": {
        "error": 0.006577409473504882,
        "error_type": "",
        "fit": "previous",
        "references": [
            {
                "exclude": false,
                "record_id": "ba-01-A-4467"
            }
        ],
        "value": 0.011743778621350471
    },
    "Ar39": {
        "error": 0.007306852228325247,
        "error_type": "",
        "fit": "previous",
        "references": [
            {
                "exclude": false,
                "record_id": "ba-01-A-4467"
            }
        ],
        "value": 0.015756899077463308
    },
    "Ar39H1": {
        "error": 0.01585705560249687,
        "error_type": "",
        "fit": "previous",
        "references": [
            {
                "exclude": false,
                "record_id": "ba-01-A-4467"
            }
        ],
        "value": 0.023381276505458376
    },
    "Ar40": {
        "error": 0.027661730551544205,
        "error_type": "",
        "fit": "previous",
        "references": [
            {
                "exclude": false,
                "record_id": "ba-01-A-4467"
            }
        ],
        "value": 1.4760163106745101
    },
    "Ar40H2": {
        "error": 0.023780264754980764,
        "error_type": "",
        "fit": "previous",
        "references": [
            {
                "exclude": false,
                "record_id": "ba-01-A-4467"
            }
        ],
        "value": 1.4451016402418042
    },
    "Ar41": {
        "error": 0.0,
        "error_type": "",
        "fit": "previous",
        "references": [
            {
                "exclude": false,
                "record_id": "ba-01-A-4467"
            }
        ],
        "value": 0.1343925542107183
    }
}