{
    "Ar36": {
        "error": 0.0019118536981313837,
        "error_type": null,
        "filter_outliers_dict": {
            "filter_outliers": false,
            "iterations": 1,
            "std_devs": 2
        },
        "fit": "linear",
        "value": 1.251605842833608
    },
    "Ar36L2": {
        "error": 0.007828776417204409,
        "error_type": null,
        "filter_outliers_dict": {
            "filter_outliers": false,
            "iterations": 1,
            "std_devs": 2
        },
        "fit": "linear",
        "value": 1.2763326071123147
    },
    "Ar37": {
        "error": 0.0069431662765409114,
        "error_type": null,
        "filter_outliers_dict": {
            "filter_outliers": false,
            "iterations": 1,
            "std_devs": 2
        },
        "fit": "linear",
        "value": 0.038998126257020524
    },
    "Ar37L1": {
        "error": 0.01639510127424364,
        "error_type": null,
        "filter_outliers_dict": {
            "filter_outliers": false,
            "iterations": 1,
            "std_devs": 2
        },
        "fit": "linear",
        "value": -0.014147121492539917
    },
    "Ar38": {
        "error": 0.015110914471851101,
        "error_type": null,
        "filter_outliers_dict": {
            "filter_outliers": false,
            "iterations": 1,
            "std_devs": 2
        },
        "fit": "linear",
        "value": 0.19319472046676173
    },
    "Ar38AX": {
        "error": 0.007118664439482072,
        "error_type": null,
        "filter_outliers_dict": {
            "filter_outliers": false,
            "iterations": 1,
            "std_devs": 2
        },
        "fit": "linear",
        "value": 0.24473953251398314
    },
    "Ar39": {
        "error": 0.007343267504906576,
        "error_type": null,
        "filter_outliers_dict": {
            "filter_outliers": false,
            "iterations": 1,
            "std_devs": 2
        },
        "fit": "linear",
        "value": 0.045031476312177784
    },
    "Ar39H1": {
        "error": 0.015671987250077776,
        "error_type": null,
        "filter_outliers_dict": {
            "filter_outliers": false,
            "iterations": 1,
            "std_devs": 2
        },
        "fit": "linear",
        "value": -0.031113096595473722
    },
    "Ar40": {
        "error": 0.05164783965383437,
        "error_type": null,
        "filter_outliers_dict": {
            "filter_outliers": false,
            "iterations": 1,
            "std_devs": 2
        },
        "fit": "parabolic",
        "value": 378.90393014352935
    },
    "Ar40H2": {
        "error": 0.04814395775365319,
        "error_type": null,
        "filter_outliers_dict": {
            "filter_outliers": false,
            "iterations": 1,
            "std_devs": 2
        },
        "fit": "parabolic",
        "value": 378.86627446445635
    },
    "Ar41": {
        "error": 0.0,
        "error_type": null,
        "filter_outliers_dict": {
            "filter_outliers": false,
            "iterations": 1,
            "std_devs": 2
        },
        "fit": "linear",
        "value": 0.0
    }
}