{
    "Ar36": {
        "error": 0.00203500075088518,
        "error_type": null,
        "filter_outliers_dict": {
            "filter_outliers": false,
            "iterations": 1,
            "std_devs": 2
        },
        "fit": "linear",
        "value": 1.2424812006724684
    },
    "Ar36L2": {
        "error": 0.007012862825744575,
        "error_type": null,
        "filter_outliers_dict": {
            "filter_outliers": false,
            "iterations": 1,
            "std_devs": 2
        },
        "fit": "linear",
        "value": 1.2683509258332695
    },
    "Ar37": {
        "error": 0.006854321634539117,
        "error_type": null,
        "filter_outliers_dict": {
            "filter_outliers": false,
            "iterations": 1,
            "std_devs": 2
        },
        "fit": "linear",
        "value": 0.029458668938947944
    },
    "Ar37L1": {
        "error": 0.01647910266212574,
        "error_type": null,
        "filter_outliers_dict": {
            "filter_outliers": false,
            "iterations": 1,
            "std_devs": 2
        },
        "fit": "linear",
        "value": -0.002870827968310564
    },
    "Ar38": {
        "error": 0.017888790205623624,
        "error_type": null,
        "filter_outliers_dict": {
            "filter_outliers": false,
            "iterations": 1,
            "std_devs": 2
        },
        "fit": "linear",
        "value": 0.21465070755067744
    },
    "Ar38AX": {
        "error": 0.006837879348185727,
        "error_type": null,
        "filter_outliers_dict": {
            "filter_outliers": false,
            "iterations": 1,
            "std_devs": 2
        },
        "fit": "linear",
        "value": 0.22633920796524715
    },
    "Ar39": {
        "error": 0.007395475231990589,
        "error_type": null,
        "filter_outliers_dict": {
            "filter_outliers": false,
            "iterations": 1,
            "std_devs": 2
        },
        "fit": "linear",
        "value": 0.04523333102566594
    },
    "Ar39H1": {
        "error": 0.014638402511028048,
        "error_type": null,
        "filter_outliers_dict": {
            "filter_outliers": false,
            "iterations": 1,
            "std_devs": 2
        },
        "fit": "linear",
        "value": -0.07067434336747529
    },
    "Ar40": {
        "error": 0.04754311656452597,
        "error_type": null,
        "filter_outliers_dict": {
            "filter_outliers": false,
            "iterations": 1,
            "std_devs": 2
        },
        "fit": "parabolic",
        "value": 376.5360838348621
    },
    "Ar40H2": {
        "error": 0.04530475586308212,
        "error_type": null,
        "filter_outliers_dict": {
            "filter_outliers": false,
            "iterations": 1,
            "std_devs": 2
        },
        "fit": "parabolic",
        "value": 376.5363136085714
    },
    "Ar41": {
        "error": 0.0,
        "error_type": null,
        "filter_outliers_dict": {
            "filter_outliers": false,
            "iterations": 1,
            "std_devs": 2
        },
        "fit": "linear",
        "value": 0.0
    }
}