{
    "Ar36": {
        "error": 0.0001901808698447446,
        "error_type": "",
        "fit": "previous",
        "references": [
            {
                "exclude": false,
                "record_id": "ba-01-A-4377"
            }
        ],
        "value": 0.008221870977719503
    },
    "Ar36L2": {
        "error": 0.0065232035196440075,
        "error_type": "",
        "fit": "previous",
        "references": [
            {
                "exclude": false,
                "record_id": "ba-01-A-4377"
            }
        ],
        "value": 0.010803156663139671
    },
    "Ar37": {
        "error": 0.0067443233199663034,
        "error_type": "",
        "fit": "previous",
        "references": [
            {
                "exclude": false,
                "record_id": "ba-01-A-4377"
            }
        ],
        "value": 0.021695704691788283
    },
    "Ar37L1": {
        "error": 0.01484343225817987,
        "error_type": "",
        "fit": "previous",
        "references": [
            {
                "exclude": false,
                "record_id": "ba-01-A-4377"
            }
        ],
        "value": 0.025221793692941384
    },
    "Ar38": {
        "error": 0.01596811213208039,
        "error_type": "",
        "fit": "previous",
        "references": [
            {
                "exclude": false,
                "record_id": "ba-01-A-4377"
            }
        ],
        "value": -0.01522940013362372
    },
    "Ar38AX": {
        "error": 0.007109797026404026,
        "error_type": "",
        "fit": "previous",
        "references": [
            {
                "exclude": false,
                "record_id": "ba-01-A-4377"
            }
        ],
        "value": 0.012652796293034821
    },
    "Ar39": {
        "error": 0.007349554841837719,
        "error_type": "",
        "fit": "previous",
        "references": [
            {
                "exclude": false,
                "record_id": "ba-01-A-4377"
            }
        ],
        "value": 0.020158750515749977
    },
    "Ar39H1": {
        "error": 0.015900213248126776,
        "error_type": "",
        "fit": "previous",
        "references": [
            {
                "exclude": false,
                "record_id": "ba-01-A-4377"
            }
        ],
        "value": 0.029444793894011667
    },
    "Ar40": {
        "error": 0.026562859632896983,
        "error_type": "",
        "fit": "previous",
        "references": [
            {
                "exclude": false,
                "record_id": "ba-01-A-4377"
            }
        ],
        "value": 2.3388968221931754
    },
    "Ar40H2": {
        "error": 0.023259709132446398,
        "error_type": "",
        "fit": "previous",
        "references": [
            {
                "exclude": false,
                "record_id": "ba-01-A-4377"
            }
        ],
        "value": 2.2847441807722384
    },
    "Ar41": {
        "error": 0.0,
        "error_type": "",
        "fit": "previous",
        "references": [
            {
                "exclude": false,
                "record_id": "ba-01-A-4377"
            }
        ],
        "value": 0.14976468694040143
    }
}