{
    "Ar36": {
        "error": 0.00016217562765409108,
        "error_type": "",
        "fit": "previous",
        "references": [
            {
                "exclude": false,
                "record_id": "ba-01-A-4478"
            }
        ],
        "value": 0.004731525233854926
    },
    "Ar36L2": {
        "error": 0.010231108536292973,
        "error_type": "",
        "fit": "previous",
        "references": [
            {
                "exclude": false,
                "record_id": "ba-01-A-4478"
            }
        ],
        "value": 0.03015457560473518
    },
    "Ar37": {
        "error": 0.007284787324470894,
        "error_type": "",
        "fit": "previous",
        "references": [
            {
                "exclude": false,
                "record_id": "ba-01-A-4478"
            }
        ],
        "value": 0.014795571197298856
    },
    "Ar37L1": {
        "error": 0.01600328277761714,
        "error_type": "",
        "fit": "previous",
        "references": [
            {
                "exclude": false,
                "record_id": "ba-01-A-4478"
            }
        ],
        "value": 0.004004268034201931
    },
    "Ar38": {
        "error": 0.016515331101266385,
        "error_type": "",
        "fit": "previous",
        "references": [
            {
                "exclude": false,
                "record_id": "ba-01-A-4478"
            }
        ],
        "value": 0.01417068840460032
    },
    "Ar38AX": {
        "error": 0.007154343727664902,
        "error_type": "",
        "fit": "previous",
        "references": [
            {
                "exclude": false,
                "record_id": "ba-01-A-4478"
            }
        ],
        "value": -0.0013299246842021044
    },
    "Ar39": {
        "error": 0.007134415334103801,
        "error_type": "",
        "fit": "previous",
        "references": [
            {
                "exclude": false,
                "record_id": "ba-01-A-4478"
            }
        ],
        "value": -0.005195038849204133
    },
    "Ar39H1": {
        "error": 0.017428133761107342,
        "error_type": "",
        "fit": "previous",
        "references": [
            {
                "exclude": false,
                "record_id": "ba-01-A-4478"
            }
        ],
        "value": 0.03959437304731562
    },
    "Ar40": {
        "error": 0.025599662990532297,
        "error_type": "",
        "fit": "previous",
        "references": [
            {
                "exclude": false,
                "record_id": "ba-01-A-4478"
            }
        ],
        "value": 1.3642069628632425
    },
    "Ar40H2": {
        "error": 0.023691630087988497,
        "error_type": "",
        "fit": "previous",
        "references": [
            {
                "exclude": false,
                "record_id": "ba-01-A-4478"
            }
        ],
        "value": 1.3518015319176495
    },
    "Ar41": {
        "error": 0.0,
        "error_type": "",
        "fit": "previous",
        "references": [
            {
                "exclude": false,
                "record_id": "ba-01-A-4478"
            }
        ],
        "value": 0.12924190071625874
    }
}